[
    {
        "term": "BUSINESS SUPPORT AND REGULATION", 
        "narrower": [
            {
                "term": "Association registration"
            }, 
            {
                "term": "Business process auditing"
            }, 
            {
                "term": "Business registration and licensing"
            }, 
            {
                "term": "Business sponsorship"
            }, 
            {
                "term": "Consumer protection"
            }, 
            {
                "term": "Fair trading compliance", 
                "narrower": [
                    {
                        "term": "Prices surveillance"
                    }, 
                    {
                        "term": "Product safety"
                    }, 
                    {
                        "term": "Trade practices compliance"
                    }
                ]
            }, 
            {
                "term": "Financial institutions regulation"
            }, 
            {
                "term": "Government procurement regulation"
            }, 
            {
                "term": "Industry assistance schemes"
            }, 
            {
                "term": "Industry development"
            }, 
            {
                "term": "Insurance regulation", 
                "narrower": [
                    {
                        "term": "General insurance"
                    }, 
                    {
                        "term": "Life insurance"
                    }
                ]
            }, 
            {
                "term": "Professional accreditation"
            }, 
            {
                "term": "Small business services", 
                "narrower": [
                    {
                        "term": "Small business advocacy"
                    }, 
                    {
                        "term": "Small business development"
                    }
                ]
            }, 
            {
                "term": "Stock market regulation"
            }
        ]
    }, 
    {
        "term": "CIVIC INFRASTRUCTURE", 
        "narrower": [
            {
                "term": "Civic management", 
                "narrower": [
                    {
                        "term": "Architectural services"
                    }, 
                    {
                        "term": "Building approval services"
                    }, 
                    {
                        "term": "Building regulations and standards"
                    }, 
                    {
                        "term": "Engineering services"
                    }, 
                    {
                        "term": "Town planning"
                    }
                ]
            }, 
            {
                "term": "Energy supply"
            }, 
            {
                "term": "Integrated services planning"
            }, 
            {
                "term": "Public housing", 
                "narrower": [
                    {
                        "term": "Public housing construction"
                    }, 
                    {
                        "term": "Public housing design"
                    }, 
                    {
                        "term": "Public housing maintenance"
                    }
                ]
            }, 
            {
                "term": "Public land management", 
                "narrower": [
                    {
                        "term": "Burial ground management"
                    }, 
                    {
                        "term": "Cultural centre management"
                    }, 
                    {
                        "term": "Garden management"
                    }, 
                    {
                        "term": "Memorial maintenance"
                    }, 
                    {
                        "term": "Recreational park management"
                    }, 
                    {
                        "term": "Sporting facilities management"
                    }
                ]
            }, 
            {
                "term": "Regional development"
            }, 
            {
                "term": "Transport network maintenance"
            }, 
            {
                "term": "Waste management"
            }
        ]
    }, 
    {
        "term": "COMMUNICATIONS", 
        "narrower": [
            {
                "term": "Advertising standards"
            }, 
            {
                "term": "Broadcasting", 
                "narrower": [
                    {
                        "term": "Broadcasting standards"
                    }, 
                    {
                        "term": "Radio broadcasting"
                    }, 
                    {
                        "term": "Television broadcasting"
                    }
                ]
            }, 
            {
                "term": "Call centre administration"
            }, 
            {
                "term": "Electronic commerce", 
                "narrower": [
                    {
                        "term": "Authentication"
                    }, 
                    {
                        "term": "Online transaction standards"
                    }
                ]
            }, 
            {
                "term": "Government media"
            }, 
            {
                "term": "Information management standards", 
                "narrower": [
                    {
                        "term": "Data management"
                    }, 
                    {
                        "term": "Information dissemination"
                    }, 
                    {
                        "term": "Information technology standards"
                    }
                ]
            }, 
            {
                "term": "Media ownership regulation"
            }, 
            {
                "term": "Postal services", 
                "narrower": [
                    {
                        "term": "Courier services"
                    }, 
                    {
                        "term": "Electronic postal services"
                    }, 
                    {
                        "term": "Retail postal services"
                    }
                ]
            }, 
            {
                "term": "Publishing", 
                "narrower": [
                    {
                        "term": "Electronic publishing"
                    }, 
                    {
                        "term": "Publishing standards"
                    }, 
                    {
                        "term": "Website development"
                    }
                ]
            }, 
            {
                "term": "Radio communication", 
                "narrower": [
                    {
                        "term": "Apparatus licensing"
                    }, 
                    {
                        "term": "Spectrum management"
                    }
                ]
            }, 
            {
                "term": "Satellite communication"
            }, 
            {
                "term": "Telecommunications", 
                "narrower": [
                    {
                        "term": "Carriage service providers"
                    }, 
                    {
                        "term": "Carrier licensing"
                    }, 
                    {
                        "term": "Equipment licensing"
                    }, 
                    {
                        "term": "Mobile telephone services"
                    }, 
                    {
                        "term": "Telephone services"
                    }
                ]
            }
        ]
    }, 
    {
        "term": "COMMUNITY SERVICES", 
        "narrower": [
            {
                "term": "Accommodation services", 
                "narrower": [
                    {
                        "term": "Defence housing"
                    }, 
                    {
                        "term": "Emergency accommodation"
                    }, 
                    {
                        "term": "Public housing entitlements"
                    }, 
                    {
                        "term": "Refuge support"
                    }
                ]
            }, 
            {
                "term": "Community support", 
                "narrower": [
                    {
                        "term": "Adoption services"
                    }, 
                    {
                        "term": "Aged care services"
                    }, 
                    {
                        "term": "Child and youth support"
                    }, 
                    {
                        "term": "Child-care services"
                    }, 
                    {
                        "term": "Defence community programs"
                    }, 
                    {
                        "term": "Family reunion programs"
                    }, 
                    {
                        "term": "Veterans' entitlements"
                    }
                ]
            }, 
            {
                "term": "Counselling services"
            }, 
            {
                "term": "Emergency services", 
                "narrower": [
                    {
                        "term": "Ambulance services"
                    }, 
                    {
                        "term": "Emergency funding"
                    }, 
                    {
                        "term": "Firefighting services"
                    }
                ]
            }, 
            {
                "term": "Financial assistance", 
                "narrower": [
                    {
                        "term": "Benefits"
                    }, 
                    {
                        "term": "Income support schemes"
                    }
                ]
            }, 
            {
                "term": "Natural disasters", 
                "narrower": [
                    {
                        "term": "Disaster recovery"
                    }, 
                    {
                        "term": "Disaster relief"
                    }
                ]
            }, 
            {
                "term": "Rural community development"
            }, 
            {
                "term": "Social justice and equity"
            }, 
            {
                "term": "Transport access schemes"
            }
        ]
    }, 
    {
        "term": "CULTURAL AFFAIRS", 
        "narrower": [
            {
                "term": "Arts development", 
                "narrower": [
                    {
                        "term": "Arts funding"
                    }, 
                    {
                        "term": "Arts incentive schemes"
                    }, 
                    {
                        "term": "Arts promotion"
                    }
                ]
            }, 
            {
                "term": "Collection access", 
                "narrower": [
                    {
                        "term": "Descriptive standards"
                    }, 
                    {
                        "term": "Finding aids development"
                    }, 
                    {
                        "term": "Reference services"
                    }
                ]
            }, 
            {
                "term": "Collection management", 
                "narrower": [
                    {
                        "term": "Artefact export regulation"
                    }, 
                    {
                        "term": "Collection accessioning"
                    }, 
                    {
                        "term": "Collection acquisition"
                    }, 
                    {
                        "term": "Collection storage"
                    }, 
                    {
                        "term": "Preservation services"
                    }
                ]
            }, 
            {
                "term": "Collection promotion", 
                "narrower": [
                    {
                        "term": "Exhibition programs"
                    }, 
                    {
                        "term": "Publicity programs"
                    }
                ]
            }, 
            {
                "term": "Cultural awards and scholarships"
            }, 
            {
                "term": "Cultural festivals"
            }, 
            {
                "term": "Cultural gifts programs"
            }, 
            {
                "term": "Multicultural heritage promotion", 
                "narrower": [
                    {
                        "term": "Multicultural festivals"
                    }, 
                    {
                        "term": "Multicultural services"
                    }
                ]
            }
        ]
    }, 
    {
        "term": "DEFENCE", 
        "narrower": [
            {
                "term": "Australian Defence Forces", 
                "narrower": [
                    {
                        "term": "Air Force"
                    }, 
                    {
                        "term": "Army"
                    }, 
                    {
                        "term": "Badges and insignia"
                    }, 
                    {
                        "term": "Cadets"
                    }, 
                    {
                        "term": "Defence force commands"
                    }, 
                    {
                        "term": "Military bands"
                    }, 
                    {
                        "term": "Navy"
                    }, 
                    {
                        "term": "Reserves"
                    }, 
                    {
                        "term": "Roulettes"
                    }
                ]
            }, 
            {
                "term": "Defence estate management"
            }, 
            {
                "term": "Defence force careers", 
                "narrower": [
                    {
                        "term": "Defence career development"
                    }, 
                    {
                        "term": "Military employment services"
                    }
                ]
            }, 
            {
                "term": "Defence strategic development", 
                "narrower": [
                    {
                        "term": "Defence efficiency review"
                    }, 
                    {
                        "term": "Defence reform program"
                    }
                ]
            }, 
            {
                "term": "Defence strategic policy", 
                "narrower": [
                    {
                        "term": "Strategic decisions"
                    }, 
                    {
                        "term": "Strategic planning"
                    }
                ]
            }, 
            {
                "term": "Defence strategic support", 
                "narrower": [
                    {
                        "term": "Capital equipment programs"
                    }, 
                    {
                        "term": "Defence industry"
                    }, 
                    {
                        "term": "Defence science and technology"
                    }, 
                    {
                        "term": "Logistics"
                    }
                ]
            }, 
            {
                "term": "Emergency management", 
                "narrower": [
                    {
                        "term": "Civil community assistance"
                    }, 
                    {
                        "term": "Disaster support"
                    }
                ]
            }, 
            {
                "term": "Military law"
            }, 
            {
                "term": "Military operations", 
                "narrower": [
                    {
                        "term": "Australian theatre of war"
                    }, 
                    {
                        "term": "Military exercises"
                    }, 
                    {
                        "term": "Special operations"
                    }, 
                    {
                        "term": "Warfare"
                    }
                ]
            }
        ]
    }, 
    {
        "term": "EDUCATION AND TRAINING", 
        "narrower": [
            {
                "term": "Arts education"
            }, 
            {
                "term": "Community education", 
                "narrower": [
                    {
                        "term": "Adult education programs"
                    }, 
                    {
                        "term": "Adult migrant education"
                    }, 
                    {
                        "term": "Road safety awareness"
                    }
                ]
            }, 
            {
                "term": "Curriculum development"
            }, 
            {
                "term": "Early childhood education"
            }, 
            {
                "term": "Military education and training", 
                "narrower": [
                    {
                        "term": "Army reserve training"
                    }, 
                    {
                        "term": "Defence college training"
                    }
                ]
            }, 
            {
                "term": "Overseas skills recognition"
            }, 
            {
                "term": "School education", 
                "narrower": [
                    {
                        "term": "Discipline programs"
                    }, 
                    {
                        "term": "School transport regulation"
                    }, 
                    {
                        "term": "Special needs programs"
                    }
                ]
            }, 
            {
                "term": "Tertiary education"
            }, 
            {
                "term": "Vocational education", 
                "narrower": [
                    {
                        "term": "Apprenticeship programs"
                    }, 
                    {
                        "term": "Hospital teaching programs"
                    }, 
                    {
                        "term": "Trainee programs"
                    }, 
                    {
                        "term": "Workplace training"
                    }
                ]
            }
        ]
    }, 
    {
        "term": "EMPLOYMENT", 
        "narrower": [
            {
                "term": "Human resources development", 
                "narrower": [
                    {
                        "term": "Occupational health and safety"
                    }, 
                    {
                        "term": "Recruitment programs"
                    }, 
                    {
                        "term": "Termination processes"
                    }, 
                    {
                        "term": "Workers compensation schemes"
                    }, 
                    {
                        "term": "Workplace discrimination monitoring"
                    }, 
                    {
                        "term": "Workplace equity and justice programs"
                    }
                ]
            }, 
            {
                "term": "Industrial awards and conditions", 
                "narrower": [
                    {
                        "term": "Award conditions"
                    }, 
                    {
                        "term": "Remuneration review"
                    }
                ]
            }, 
            {
                "term": "Labour market programs", 
                "narrower": [
                    {
                        "term": "Employment services marketing"
                    }, 
                    {
                        "term": "Job placement programs"
                    }, 
                    {
                        "term": "Job vacancy data management"
                    }
                ]
            }, 
            {
                "term": "Workplace agreement processes", 
                "narrower": [
                    {
                        "term": "Agreement bargaining processes"
                    }, 
                    {
                        "term": "Agreement dispute mediation"
                    }, 
                    {
                        "term": "Certified employment conditions"
                    }, 
                    {
                        "term": "Employment advocacy services"
                    }
                ]
            }
        ]
    }, 
    {
        "term": "ENVIRONMENT", 
        "narrower": [
            {
                "term": "Built environment", 
                "narrower": [
                    {
                        "term": "Building acoustics"
                    }, 
                    {
                        "term": "Building preservation"
                    }
                ]
            }, 
            {
                "term": "Climate information services"
            }, 
            {
                "term": "Conservation programs", 
                "narrower": [
                    {
                        "term": "Endangered species protection"
                    }, 
                    {
                        "term": "Landcare programs"
                    }, 
                    {
                        "term": "Soil preservation programs"
                    }
                ]
            }, 
            {
                "term": "Environmental impact assessment"
            }, 
            {
                "term": "Historic relic protection"
            }, 
            {
                "term": "Marine life protection programs"
            }, 
            {
                "term": "Natural heritage protection", 
                "narrower": [
                    {
                        "term": "National park management"
                    }, 
                    {
                        "term": "Nature reserve management"
                    }, 
                    {
                        "term": "Wilderness area management"
                    }, 
                    {
                        "term": "Wildlife sanctuary management"
                    }
                ]
            }, 
            {
                "term": "Oceans governance"
            }, 
            {
                "term": "Pollutant prevention programs"
            }, 
            {
                "term": "World heritage listings"
            }
        ]
    }, 
    {
        "term": "FINANCE MANAGEMENT", 
        "narrower": [
            {
                "term": "Commonwealth State funding"
            }, 
            {
                "term": "Currency", 
                "narrower": [
                    {
                        "term": "Counterfeiting control"
                    }
                ]
            }, 
            {
                "term": "Financial investment", 
                "narrower": [
                    {
                        "term": "Investment scheme regulation"
                    }
                ]
            }, 
            {
                "term": "Financial system management", 
                "narrower": [
                    {
                        "term": "Financial system monitoring"
                    }, 
                    {
                        "term": "Payments management"
                    }
                ]
            }, 
            {
                "term": "Fiscal policy", 
                "narrower": [
                    {
                        "term": "Public borrowing"
                    }, 
                    {
                        "term": "Public debt"
                    }, 
                    {
                        "term": "Public expenditure"
                    }
                ]
            }, 
            {
                "term": "Foreign investment control"
            }, 
            {
                "term": "International monetary regulation"
            }, 
            {
                "term": "Monetary policy", 
                "narrower": [
                    {
                        "term": "Exchange rates"
                    }, 
                    {
                        "term": "Inflation"
                    }, 
                    {
                        "term": "Interest rates"
                    }
                ]
            }, 
            {
                "term": "Resource management", 
                "narrower": [
                    {
                        "term": "Contract management"
                    }, 
                    {
                        "term": "Financial administration"
                    }, 
                    {
                        "term": "Financial budgeting"
                    }
                ]
            }, 
            {
                "term": "Retirement income", 
                "narrower": [
                    {
                        "term": "Asset assessment"
                    }, 
                    {
                        "term": "Retirement saving"
                    }, 
                    {
                        "term": "Superannuation regulation"
                    }
                ]
            }, 
            {
                "term": "Statistical analysis"
            }, 
            {
                "term": "Taxation", 
                "narrower": [
                    {
                        "term": "Income assessment"
                    }, 
                    {
                        "term": "Revenue raising"
                    }, 
                    {
                        "term": "Taxation compliance"
                    }
                ]
            }
        ]
    }, 
    {
        "term": "GOVERNANCE", 
        "narrower": [
            {
                "term": "Civic celebrations"
            }, 
            {
                "term": "Constitutional matters", 
                "narrower": [
                    {
                        "term": "Constitutional conventions"
                    }, 
                    {
                        "term": "Constitutional referenda"
                    }
                ]
            }, 
            {
                "term": "Electoral matters", 
                "narrower": [
                    {
                        "term": "Declaration of interests"
                    }, 
                    {
                        "term": "Election campaigning"
                    }, 
                    {
                        "term": "Electoral boundary assessment"
                    }
                ]
            }, 
            {
                "term": "Honours and awards programs"
            }, 
            {
                "term": "Intergovernmental relations", 
                "narrower": [
                    {
                        "term": "Cross-border cooperation"
                    }, 
                    {
                        "term": "Intergovernment policy dissemination"
                    }
                ]
            }, 
            {
                "term": "Legislative drafting", 
                "narrower": [
                    {
                        "term": "Draft Bill amendment process"
                    }, 
                    {
                        "term": "Legislation review"
                    }, 
                    {
                        "term": "Preparation of legislative regulations"
                    }
                ]
            }, 
            {
                "term": "Official protocol", 
                "narrower": [
                    {
                        "term": "Ceremonial events and representation"
                    }, 
                    {
                        "term": "Head of Government protocol"
                    }, 
                    {
                        "term": "Official establishment management"
                    }, 
                    {
                        "term": "Official hospitality"
                    }, 
                    {
                        "term": "Official visits"
                    }
                ]
            }, 
            {
                "term": "Parliamentary chamber support", 
                "narrower": [
                    {
                        "term": "Hansard services"
                    }, 
                    {
                        "term": "Parliamentary papers"
                    }, 
                    {
                        "term": "Tabling of official documents"
                    }
                ]
            }, 
            {
                "term": "Parliamentary committee and member support"
            }, 
            {
                "term": "Population census", 
                "narrower": [
                    {
                        "term": "Demographic surveys"
                    }, 
                    {
                        "term": "Household census"
                    }, 
                    {
                        "term": "Population distribution analysis"
                    }
                ]
            }, 
            {
                "term": "Public administration", 
                "narrower": [
                    {
                        "term": "Government auditing"
                    }, 
                    {
                        "term": "Public service"
                    }, 
                    {
                        "term": "Territories administration"
                    }
                ]
            }, 
            {
                "term": "Statistics"
            }
        ]
    }, 
    {
        "term": "HEALTH CARE", 
        "narrower": [
            {
                "term": "Community health services", 
                "narrower": [
                    {
                        "term": "Clinical health services"
                    }, 
                    {
                        "term": "Health promotion"
                    }, 
                    {
                        "term": "Primary health care"
                    }
                ]
            }, 
            {
                "term": "Health insurance schemes"
            }, 
            {
                "term": "Health protocol administration", 
                "narrower": [
                    {
                        "term": "Drugs and poisons regulation"
                    }, 
                    {
                        "term": "Food hygiene regulation"
                    }, 
                    {
                        "term": "Practitioner discipline"
                    }, 
                    {
                        "term": "Practitioner registration"
                    }
                ]
            }, 
            {
                "term": "Hospital services", 
                "narrower": [
                    {
                        "term": "Hospital administration"
                    }, 
                    {
                        "term": "Patient care"
                    }, 
                    {
                        "term": "Pharmaceutical and drug support"
                    }
                ]
            }, 
            {
                "term": "Medical research", 
                "narrower": [
                    {
                        "term": "Ethical compliance"
                    }, 
                    {
                        "term": "Medical aids regulation"
                    }, 
                    {
                        "term": "Medical research funding"
                    }, 
                    {
                        "term": "National referral laboratory services"
                    }, 
                    {
                        "term": "Population-based research"
                    }
                ]
            }, 
            {
                "term": "Public health services", 
                "narrower": [
                    {
                        "term": "Epidemiology"
                    }, 
                    {
                        "term": "Health disaster preparedness"
                    }, 
                    {
                        "term": "Health hazard prevention"
                    }, 
                    {
                        "term": "Medical quarantine services"
                    }, 
                    {
                        "term": "Notifiable disease management"
                    }
                ]
            }, 
            {
                "term": "Special needs services", 
                "narrower": [
                    {
                        "term": "Dental health services"
                    }, 
                    {
                        "term": "Independent living services"
                    }, 
                    {
                        "term": "Mental health services"
                    }, 
                    {
                        "term": "Residential services"
                    }
                ]
            }, 
            {
                "term": "Veterans' health services"
            }
        ]
    }, 
    {
        "term": "IMMIGRATION", 
        "narrower": [
            {
                "term": "Citizenship", 
                "narrower": [
                    {
                        "term": "Naturalisation assessment"
                    }, 
                    {
                        "term": "Presentation arrangements"
                    }
                ]
            }, 
            {
                "term": "Deportation"
            }, 
            {
                "term": "Detention programs"
            }, 
            {
                "term": "Migrant services", 
                "narrower": [
                    {
                        "term": "Interpreter services"
                    }, 
                    {
                        "term": "Migrant accommodation services"
                    }, 
                    {
                        "term": "Migrant settlement programs"
                    }
                ]
            }, 
            {
                "term": "Refugee services"
            }, 
            {
                "term": "Travel authorisation", 
                "narrower": [
                    {
                        "term": "Permanent entry arrangements"
                    }, 
                    {
                        "term": "Temporary entry arrangements"
                    }
                ]
            }
        ]
    }, 
    {
        "term": "INDIGENOUS AFFAIRS", 
        "narrower": [
            {
                "term": "Indigenous cultural heritage", 
                "narrower": [
                    {
                        "term": "Cultural artefact repatriation"
                    }
                ]
            }, 
            {
                "term": "Indigenous enterprise development"
            }, 
            {
                "term": "Indigenous health services"
            }, 
            {
                "term": "Indigenous heritage conservation"
            }, 
            {
                "term": "Indigenous reconciliation"
            }, 
            {
                "term": "Indigenous welfare programs"
            }
        ]
    }, 
    {
        "term": "INTERNATIONAL RELATIONS", 
        "narrower": [
            {
                "term": "Consular services"
            }, 
            {
                "term": "Defence liaison", 
                "narrower": [
                    {
                        "term": "Defence attach\u00e9s"
                    }, 
                    {
                        "term": "Defence cooperation programs"
                    }, 
                    {
                        "term": "Defence personnel exchanges"
                    }, 
                    {
                        "term": "Military advisors"
                    }
                ]
            }, 
            {
                "term": "Diplomatic missions"
            }, 
            {
                "term": "International affairs", 
                "narrower": [
                    {
                        "term": "Disarmament and arms control"
                    }, 
                    {
                        "term": "Nuclear safeguards"
                    }
                ]
            }, 
            {
                "term": "International treaties", 
                "narrower": [
                    {
                        "term": "Treaty administration"
                    }
                ]
            }, 
            {
                "term": "Overseas aid programs", 
                "narrower": [
                    {
                        "term": "Development assistance programs"
                    }, 
                    {
                        "term": "Overseas student scholarship programs"
                    }
                ]
            }, 
            {
                "term": "Overseas promotion"
            }, 
            {
                "term": "Passport services"
            }
        ]
    }, 
    {
        "term": "JUSTICE ADMINISTRATION", 
        "narrower": [
            {
                "term": "Administrative law", 
                "narrower": [
                    {
                        "term": "Administrative decision appeal"
                    }, 
                    {
                        "term": "Administrative decision review"
                    }, 
                    {
                        "term": "Censorship standards"
                    }, 
                    {
                        "term": "Copyright regulation"
                    }, 
                    {
                        "term": "Recordkeeping standards"
                    }
                ]
            }, 
            {
                "term": "Associations and corporate law", 
                "narrower": [
                    {
                        "term": "Bankruptcy proceedings"
                    }, 
                    {
                        "term": "Merger regulation"
                    }
                ]
            }, 
            {
                "term": "Civil law", 
                "narrower": [
                    {
                        "term": "Civil registration"
                    }, 
                    {
                        "term": "Conveyancing"
                    }, 
                    {
                        "term": "Dispute mediation programs"
                    }, 
                    {
                        "term": "Family law proceedings"
                    }, 
                    {
                        "term": "Probate applications"
                    }
                ]
            }, 
            {
                "term": "Commissions of inquiry"
            }, 
            {
                "term": "Coronial law"
            }, 
            {
                "term": "Court reporting"
            }, 
            {
                "term": "Criminal law"
            }, 
            {
                "term": "Human rights obligations"
            }, 
            {
                "term": "Juvenile justice"
            }, 
            {
                "term": "Legal aid services"
            }, 
            {
                "term": "Local laws and ordinances"
            }, 
            {
                "term": "Native title claims", 
                "narrower": [
                    {
                        "term": "Native title mediation programs"
                    }, 
                    {
                        "term": "Native title settlement negotiations"
                    }
                ]
            }, 
            {
                "term": "Privacy guideline monitoring"
            }, 
            {
                "term": "Prosecution services"
            }
        ]
    }, 
    {
        "term": "MARITIME SERVICES", 
        "narrower": [
            {
                "term": "Cargo control"
            }, 
            {
                "term": "Harbour management"
            }, 
            {
                "term": "Marina management"
            }, 
            {
                "term": "Navigation", 
                "narrower": [
                    {
                        "term": "Charting sea lanes"
                    }, 
                    {
                        "term": "Light station maintenance"
                    }, 
                    {
                        "term": "Navigation systems development"
                    }
                ]
            }, 
            {
                "term": "Pilotage management"
            }, 
            {
                "term": "Port regulation"
            }, 
            {
                "term": "Sea passengers"
            }, 
            {
                "term": "Search and rescue", 
                "narrower": [
                    {
                        "term": "Rescue coordination"
                    }, 
                    {
                        "term": "Search technology development"
                    }
                ]
            }, 
            {
                "term": "Ship personnel", 
                "narrower": [
                    {
                        "term": "Personnel safety standards"
                    }, 
                    {
                        "term": "Pilot licensing"
                    }
                ]
            }, 
            {
                "term": "Ship safety", 
                "narrower": [
                    {
                        "term": "Seaworthiness"
                    }, 
                    {
                        "term": "Ship commissioning"
                    }, 
                    {
                        "term": "Ship inspection"
                    }
                ]
            }
        ]
    }, 
    {
        "term": "NATURAL RESOURCES", 
        "narrower": [
            {
                "term": "Crown land administration"
            }, 
            {
                "term": "Energy resources", 
                "narrower": [
                    {
                        "term": "Fossil fuel management"
                    }, 
                    {
                        "term": "Renewable energy development"
                    }
                ]
            }, 
            {
                "term": "Land use planning", 
                "narrower": [
                    {
                        "term": "Land use zoning"
                    }
                ]
            }, 
            {
                "term": "Land valuation"
            }, 
            {
                "term": "Mineral resources", 
                "narrower": [
                    {
                        "term": "Land rehabilitation programs"
                    }, 
                    {
                        "term": "Mining regulations"
                    }
                ]
            }, 
            {
                "term": "Pollution emission control"
            }, 
            {
                "term": "Water resources", 
                "narrower": [
                    {
                        "term": "Water conservation plans"
                    }, 
                    {
                        "term": "Water quality monitoring"
                    }, 
                    {
                        "term": "Water usage management"
                    }, 
                    {
                        "term": "Waterway management"
                    }
                ]
            }
        ]
    }, 
    {
        "term": "PRIMARY INDUSTRIES", 
        "narrower": [
            {
                "term": "Chemical and pesticide regulation"
            }, 
            {
                "term": "Marine and rural regulation", 
                "narrower": [
                    {
                        "term": "Agricultural industry"
                    }, 
                    {
                        "term": "Fisheries industry"
                    }, 
                    {
                        "term": "Food quality assurance"
                    }, 
                    {
                        "term": "Forestry industry"
                    }
                ]
            }, 
            {
                "term": "Marine and rural support", 
                "narrower": [
                    {
                        "term": "Aquaculture industry"
                    }, 
                    {
                        "term": "Horticultural industry"
                    }, 
                    {
                        "term": "Pastoral industry"
                    }, 
                    {
                        "term": "Silvicultural industry"
                    }, 
                    {
                        "term": "Viticultural industry"
                    }
                ]
            }, 
            {
                "term": "Quarantine"
            }, 
            {
                "term": "Rural field day promotion"
            }, 
            {
                "term": "Rural partnership programs"
            }
        ]
    }, 
    {
        "term": "SCIENCE", 
        "narrower": [
            {
                "term": "Agricultural sciences"
            }, 
            {
                "term": "Animal and veterinary sciences"
            }, 
            {
                "term": "Applied sciences", 
                "narrower": [
                    {
                        "term": "Engineering and technology sciences"
                    }, 
                    {
                        "term": "Weights and measures standards"
                    }
                ]
            }, 
            {
                "term": "Biological sciences", 
                "narrower": [
                    {
                        "term": "Biochemistry"
                    }, 
                    {
                        "term": "Biodiversity preservation"
                    }, 
                    {
                        "term": "Biotechnology development"
                    }, 
                    {
                        "term": "Botany"
                    }, 
                    {
                        "term": "Entomology"
                    }, 
                    {
                        "term": "Genetic engineering"
                    }, 
                    {
                        "term": "Physiology"
                    }
                ]
            }, 
            {
                "term": "Earth sciences", 
                "narrower": [
                    {
                        "term": "Atmospheric sciences"
                    }, 
                    {
                        "term": "Hydrology"
                    }, 
                    {
                        "term": "Mineral exploration"
                    }, 
                    {
                        "term": "Oceanography"
                    }, 
                    {
                        "term": "Seismology"
                    }
                ]
            }, 
            {
                "term": "Mathematical sciences"
            }, 
            {
                "term": "Medical and health sciences"
            }, 
            {
                "term": "Physical sciences", 
                "narrower": [
                    {
                        "term": "Astronomical sciences"
                    }, 
                    {
                        "term": "Atomic and molecular sciences"
                    }, 
                    {
                        "term": "Nuclear sciences"
                    }
                ]
            }, 
            {
                "term": "Spatial information research"
            }
        ]
    }, 
    {
        "term": "SECURITY", 
        "narrower": [
            {
                "term": "Corrective services", 
                "narrower": [
                    {
                        "term": "Community based corrections"
                    }, 
                    {
                        "term": "Detention centre management"
                    }
                ]
            }, 
            {
                "term": "External security", 
                "narrower": [
                    {
                        "term": "Peacekeeping forces"
                    }
                ]
            }, 
            {
                "term": "Information security"
            }, 
            {
                "term": "Intelligence", 
                "narrower": [
                    {
                        "term": "Forensic analysis"
                    }, 
                    {
                        "term": "Intelligence liaison"
                    }, 
                    {
                        "term": "Intelligence support"
                    }
                ]
            }, 
            {
                "term": "Law enforcement", 
                "narrower": [
                    {
                        "term": "Community policing"
                    }, 
                    {
                        "term": "Criminology"
                    }, 
                    {
                        "term": "Police administration"
                    }, 
                    {
                        "term": "Protective services"
                    }
                ]
            }, 
            {
                "term": "National security", 
                "narrower": [
                    {
                        "term": "Coastal surveillance"
                    }
                ]
            }
        ]
    }, 
    {
        "term": "SPORT AND RECREATION", 
        "narrower": [
            {
                "term": "Caravan and camping services"
            }, 
            {
                "term": "Community recreational programs", 
                "narrower": [
                    {
                        "term": "Gambling support services"
                    }, 
                    {
                        "term": "Public fitness promotion"
                    }, 
                    {
                        "term": "Social club support"
                    }, 
                    {
                        "term": "Volunteer support programs"
                    }
                ]
            }, 
            {
                "term": "Gaming industry regulation"
            }, 
            {
                "term": "Park and reserve services"
            }, 
            {
                "term": "Sport and fitness development", 
                "narrower": [
                    {
                        "term": "Athlete scholarship programs"
                    }, 
                    {
                        "term": "Fundraising and donation schemes"
                    }, 
                    {
                        "term": "Games administration"
                    }, 
                    {
                        "term": "Games promotion"
                    }, 
                    {
                        "term": "Sporting grants administration"
                    }
                ]
            }, 
            {
                "term": "Sports drugs monitoring", 
                "narrower": [
                    {
                        "term": "Doping detection research"
                    }
                ]
            }
        ]
    }, 
    {
        "term": "TOURISM", 
        "narrower": [
            {
                "term": "Tourism industry development"
            }, 
            {
                "term": "Tourist event promotion", 
                "narrower": [
                    {
                        "term": "Advertising campaigns"
                    }
                ]
            }, 
            {
                "term": "Travel missions"
            }
        ]
    }, 
    {
        "term": "TRADE", 
        "narrower": [
            {
                "term": "Export regulation", 
                "narrower": [
                    {
                        "term": "Export promotion"
                    }, 
                    {
                        "term": "Prohibited export control"
                    }
                ]
            }, 
            {
                "term": "Import regulation", 
                "narrower": [
                    {
                        "term": "Prohibited import control"
                    }, 
                    {
                        "term": "Tariff regulation"
                    }
                ]
            }, 
            {
                "term": "Intellectual property management", 
                "narrower": [
                    {
                        "term": "Copyright registration"
                    }, 
                    {
                        "term": "Design registration"
                    }, 
                    {
                        "term": "Patent registration"
                    }, 
                    {
                        "term": "Trademark registration"
                    }
                ]
            }, 
            {
                "term": "International trade agreements"
            }, 
            {
                "term": "Interstate trade agreements"
            }, 
            {
                "term": "Trade development programs"
            }, 
            {
                "term": "Trade expositions"
            }
        ]
    }, 
    {
        "term": "TRANSPORT", 
        "narrower": [
            {
                "term": "Air transport", 
                "narrower": [
                    {
                        "term": "Air transport safety"
                    }, 
                    {
                        "term": "Aircraft standards"
                    }, 
                    {
                        "term": "Airport services"
                    }
                ]
            }, 
            {
                "term": "Freight movement regulation"
            }, 
            {
                "term": "Passenger services"
            }, 
            {
                "term": "Rail transport", 
                "narrower": [
                    {
                        "term": "Rail harmonisation standards"
                    }, 
                    {
                        "term": "Rail land acquisition regulation"
                    }, 
                    {
                        "term": "Rail transport safety"
                    }, 
                    {
                        "term": "Railway maintenance"
                    }, 
                    {
                        "term": "Rolling stock regulation"
                    }
                ]
            }, 
            {
                "term": "Road transport", 
                "narrower": [
                    {
                        "term": "Driving licences administration"
                    }, 
                    {
                        "term": "Road surface maintenance"
                    }, 
                    {
                        "term": "Road traffic regulation"
                    }, 
                    {
                        "term": "Road transport safety"
                    }, 
                    {
                        "term": "Vehicle registration"
                    }, 
                    {
                        "term": "Vehicle standards"
                    }
                ]
            }, 
            {
                "term": "Transport infrastructure development"
            }
        ]
    }
]